{"positions":[{"title":"President","runners":[{"name":"Abe","year":2015,"concentration":"Biology"},{"name":"Bob","year":2015,"concentration":"Chemistry"},{"name":"Charles","year":2015,"concentration":"Engineering"}]},{"title":"Vice President","runners":[{"name":"David","year":2016,"concentration":"Physics"},{"name":"Eugene","year":2016,"concentration":"Math"},{"name":"Felicia","year":2016,"concentration":"History"}]},{"title":"Secretary","runners":[{"name":"Grace","year":2016,"concentration":"MCM"},{"name":"Henrietta","year":2016,"concentration":""}]},{"title":"Social Chair","runners":[{"name":"Isaac","year":2017,"concentration":""}]},{"title":"Freshman Representative","runners":[{"name":"Jill","year":2018,"concentration":""},{"name":"Kelsey","year":2018,"concentration":""}]}],"title":"Test Election","start":"2013-01-01T05:00:00.000Z","end":"2013-01-31T05:00:00.000Z","notes":""}